[
    {
        "id": 18021137683066433,
        "created_at": 1548368214,
        "text": "@willow_921 Right ha. Tbh though feminism isn't really feminism any more. At one point in time it meant/stood for something but nowadays its become just an excuse to complain about dumb shit and made up shit while blaming everything on everybody but yourself. #fuckfeminism",
        "owner": {
            "id": "8728819764",
            "is_verified": false,
            "profile_pic_url": "https://scontent-dus1-1.cdninstagram.com/vp/587dcb233a1645bc77e41f4d751d5bdc/5D38A483/t51.2885-19/s150x150/52040704_592436691229461_4663980071344668672_n.jpg?_nc_ht=scontent-dus1-1.cdninstagram.com",
            "username": "viking.polska"
        },
        "answers": []
    },
    {
        "id": 18006511450126851,
        "created_at": 1548367962,
        "text": "@polish.viking27 Ofcourse it was, it's funny how much modern feminists hate men but at the end of the day they're gonna want what's in our pants \ud83e\udd37\ud83c\udffb\u200d\u2642\ufe0f it's in their DNA lol",
        "owner": {
            "id": "7849180575",
            "is_verified": false,
            "profile_pic_url": "https://scontent-dus1-1.cdninstagram.com/vp/f2b2e177aaf45597bd86af4d908cac25/5D440979/t51.2885-19/s150x150/54457881_385445292288594_1285701140117192704_n.jpg?_nc_ht=scontent-dus1-1.cdninstagram.com",
            "username": "willow_921"
        },
        "answers": []
    },
    {
        "id": 17953353292227207,
        "created_at": 1548367901,
        "text": "@willow_921 True and I heard that the add was actually written and directed by a female",
        "owner": {
            "id": "8728819764",
            "is_verified": false,
            "profile_pic_url": "https://scontent-dus1-1.cdninstagram.com/vp/587dcb233a1645bc77e41f4d751d5bdc/5D38A483/t51.2885-19/s150x150/52040704_592436691229461_4663980071344668672_n.jpg?_nc_ht=scontent-dus1-1.cdninstagram.com",
            "username": "viking.polska"
        },
        "answers": []
    },
    {
        "id": 18009960115110426,
        "created_at": 1548367688,
        "text": "@polish.viking27 soy boys and feminists",
        "owner": {
            "id": "7849180575",
            "is_verified": false,
            "profile_pic_url": "https://scontent-dus1-1.cdninstagram.com/vp/f2b2e177aaf45597bd86af4d908cac25/5D440979/t51.2885-19/s150x150/54457881_385445292288594_1285701140117192704_n.jpg?_nc_ht=scontent-dus1-1.cdninstagram.com",
            "username": "willow_921"
        },
        "answers": []
    },
    {
        "id": 18026217955057481,
        "created_at": 1548367371,
        "text": "@willow_921 Gillettes gone gay ig. Must be owned by a bunch of soy boys now \ud83e\udd37\ud83e\udd37",
        "owner": {
            "id": "8728819764",
            "is_verified": false,
            "profile_pic_url": "https://scontent-dus1-1.cdninstagram.com/vp/587dcb233a1645bc77e41f4d751d5bdc/5D38A483/t51.2885-19/s150x150/52040704_592436691229461_4663980071344668672_n.jpg?_nc_ht=scontent-dus1-1.cdninstagram.com",
            "username": "viking.polska"
        },
        "answers": []
    },
    {
        "id": 17950100752235683,
        "created_at": 1548112022,
        "text": "Haha",
        "owner": {
            "id": "7849180575",
            "is_verified": false,
            "profile_pic_url": "https://scontent-dus1-1.cdninstagram.com/vp/f2b2e177aaf45597bd86af4d908cac25/5D440979/t51.2885-19/s150x150/54457881_385445292288594_1285701140117192704_n.jpg?_nc_ht=scontent-dus1-1.cdninstagram.com",
            "username": "willow_921"
        },
        "answers": []
    }
]